MyGraph/MyGraph.py
MyGraph/__init__.py
pakage_test_jinwook-0.0.1.dist-info/LICENSE
pakage_test_jinwook-0.0.1.dist-info/METADATA
pakage_test_jinwook-0.0.1.dist-info/WHEEL
pakage_test_jinwook-0.0.1.dist-info/top_level.txt
pakage_test_jinwook-0.0.1.dist-info/RECORD
