Metadata-Version: 2.1
Name: pakage-test-jinwook
Version: 0.0.1
Summary: jinwook pakage test
Home-page: https://github.com/jinwook213/jinwook213.git
Author: Jinwook_Lee
Author-email: jinwook213@cau.ac.kr
License: jinwook
License-File: LICENSE
